nasa_mcp/__init__.py
nasa_mcp/server.py
nasa_mcp-0.1.0.dist-info/licenses/LICENSE
nasa_mcp-0.1.0.dist-info/METADATA
nasa_mcp-0.1.0.dist-info/WHEEL
nasa_mcp-0.1.0.dist-info/entry_points.txt
nasa_mcp-0.1.0.dist-info/top_level.txt
nasa_mcp-0.1.0.dist-info/RECORD
